{
  "project_info": {
    "project_number": "976122699498",
    "firebase_url": "https://na-tech-project-2.firebaseio.com",
    "project_id": "na-tech-project-2",
    "storage_bucket": "na-tech-project-2.appspot.com"
  },
  "client": [
    {
      "client_info": {
        "mobilesdk_app_id": "1:976122699498:android:d0b399adb04094adb60193",
        "android_client_info": {
          "package_name": "com.edupolt.natech2"
        }
      },
      "oauth_client": [
        {
          "client_id": "976122699498-e6jo795qghglksl09pp10atpu402ft1b.apps.googleusercontent.com",
          "client_type": 1,
          "android_info": {
            "package_name": "com.edupolt.natech2",
            "certificate_hash": "c7bd149d26d5e8b70943c8369efa427f2b3bca7e"
          }
        },
        {
          "client_id": "976122699498-kfgv7at3oltmh7g9g1t03veg66atop9k.apps.googleusercontent.com",
          "client_type": 3
        }
      ],
      "api_key": [
        {
          "current_key": "AIzaSyDCcrtoW36s0EeaF9i0ZaiUkdGermFkJcQ"
        }
      ],
      "services": {
        "appinvite_service": {
          "other_platform_oauth_client": [
            {
              "client_id": "976122699498-kfgv7at3oltmh7g9g1t03veg66atop9k.apps.googleusercontent.com",
              "client_type": 3
            }
          ]
        }
      }
    }
  ],
  "configuration_version": "1"
}